brainowl/__init__.py
brainowl/brainowl.py
brainowl/solver.py
brainowl-0.1.dist-info/LICENSE
brainowl-0.1.dist-info/METADATA
brainowl-0.1.dist-info/WHEEL
brainowl-0.1.dist-info/top_level.txt
brainowl-0.1.dist-info/RECORD
