Metadata-Version: 2.1
Name: brainowl
Version: 0.1
Summary: Classifier tuned for neuroimaging based on SpaRSA solver
Home-page: https://github.com/jpvaldes/brainowl
Author: Jose P Valdes Herrera
Author-email: jpvaldesherrera@gmail.com
License: BSD (3-clause)
Download-URL: https://github.com/jpvaldes/brainowl.git
Platform: UNKNOWN
Classifier: License :: OSI Approved :: BSD License
Classifier: Programming Language :: Python
Classifier: Programming Language :: Python :: 3
Classifier: Intended Audience :: Science/Research
Classifier: Development Status :: 3 - Alpha
Classifier: Topic :: Scientific/Engineering
Classifier: Topic :: Software Development
Requires-Python: >=3.5.0
Requires-Dist: numpy
Requires-Dist: scipy
Requires-Dist: scikit-learn
